matteridge/__init__.py
matteridge/__main__.py
matteridge/api.py
matteridge/cache.py
matteridge/command.py
matteridge/config.py
matteridge/contact.py
matteridge/events.py
matteridge/gateway.py
matteridge/group.py
matteridge/session.py
matteridge/util.py
matteridge/websocket.py
matteridge-0.3.0.dist-info/licenses/LICENSE
matteridge-0.3.0.dist-info/METADATA
matteridge-0.3.0.dist-info/WHEEL
matteridge-0.3.0.dist-info/entry_points.txt
matteridge-0.3.0.dist-info/top_level.txt
matteridge-0.3.0.dist-info/RECORD
