Metadata-Version: 2.4
Name: matteridge
Version: 0.3.0
Summary: A Mattermost/XMPP gateway
Author-email: Nicolas Cedilnik <nicoco@nicoco.fr>
License-Expression: AGPL-3.0-or-later
Project-URL: Homepage, https://codeberg.org/slidge/matteridge
Project-URL: Issues, https://codeberg.org/slidge/matteridge/issues
Project-URL: Repository, https://codeberg.org/slidge/matteridge
Project-URL: Chat room, https://slidge.im/xmpp-web/#/guest?join=slidge@conference.nicoco.fr
Project-URL: Documentation, https://slidge.im/docs/matteridge/main
Project-URL: changelog, https://codeberg.org/slidge/matteridge/releases
Keywords: xmpp,gateway,bridge,instant messaging,chat,mattermost
Classifier: Topic :: Internet :: XMPP
Requires-Python: >=3.11
License-File: LICENSE
Requires-Dist: mattermost-api-reference-client<5,>=4.1
Requires-Dist: emoji<3,>=2.2.0
Requires-Dist: async-lru<3,>=2.0.4
Requires-Dist: slidge<0.4,>=0.3alpha3
Dynamic: license-file
